Workbook

Sheet 버킷분류
A1: 진영 | B1: 버킷 | C1: 버킷명 | D1: 티커 | E1: ETF명 | F1: AUM(억원) | G1: 기초지수 | H1: 원본_위험안전 | I1: 원본_자산군 | J1: 대표ETF
A2: 방어 | B2: A1 | C2: 현금성 | D2: A459580 | E2: KODEX CD금리액티브(합성) | F2: 79731 | G2: KAP 양도성예금증서(CD)금리지수(총수익지수) | H2: 안전 | I2: 금리연계형/초단기채권 | J2: ★
A3: 방어 | B3: A1 | C3: 현금성 | D3: A488770 | E3: KODEX 머니마켓액티브 | F3: 72891 | G3: KAP MMF 지수(TR) | H3: 안전 | I3: 금리연계형/초단기채권
A4: 방어 | B4: A1 | C4: 현금성 | D4: A423160 | E4: KODEX KOFR금리액티브(합성) | F4: 43045 | G4: KOFR 지수 | H4: 안전 | I4: 금리연계형/초단기채권
A5: 방어 | B5: A1 | C5: 현금성 | D5: A455890 | E5: RISE 머니마켓액티브 | F5: 22406 | G5: KIS 시가평가 MMF 지수 (총수익지수) | H5: 안전 | I5: 금리연계형/초단기채권
A6: 방어 | B6: A1 | C6: 현금성 | D6: A0061Z0 | E6: RISE 단기특수은행채액티브 | F6: 12843 | G6: KAP 단기 특수은행채 지수(시장가격) | H6: 안전 | I6: 국내채권_회사채
A7: 방어 | B7: A1 | C7: 현금성 | D7: A157450 | E7: TIGER 단기통안채 | F7: 9750 | G7: KIS MSB 6M(총수익) | H7: 안전 | I7: 국내채권_종합
A8: 방어 | B8: A1 | C8: 현금성 | D8: A469830 | E8: SOL 초단기채권액티브 | F8: 9092 | G8: KAP 단기자금시장지수 | H8: 안전 | I8: 금리연계형/초단기채권
A9: 방어 | B9: A1 | C9: 현금성 | D9: A153130 | E9: KODEX 단기채권 | F9: 7321 | G9: KRW Cash Index(총수익) | H9: 안전 | I9: 금리연계형/초단기채권
A10: 방어 | B10: A1 | C10: 현금성 | D10: A456610 | E10: TIGER 미국달러SOFR금리액티브(합성) | F10: 6550 | G10: Solactive SOFR Daily Total Return Index | H10: 안전 | I10: 금리연계형/초단기채권
A11: 방어 | B11: A1 | C11: 현금성 | D11: A329750 | E11: TIGER 미국달러단기채권액티브 | F11: 4708 | G11: KIS U.S. TREASURY BOND 0-1Y 지수 | H11: 안전 | I11: 해외채권_종합
A12: 방어 | B12: A1 | C12: 현금성 | D12: A196230 | E12: RISE 단기통안채 | F12: 2081 | G12: KIS MSB 5M Index(총수익) | H12: 안전 | I12: 금리연계형/초단기채권
A13: 방어 | B13: A1 | C13: 현금성 | D13: A272560 | E13: RISE 단기국공채액티브 | F13: 1915 | G13: KIS 종합채권국공채3M~1.5Y지수 | H13: 안전 | I13: 국내채권_종합
A14: 방어 | B14: A1 | C14: 현금성 | D14: A455960 | E14: RISE 미국달러SOFR금리액티브(합성) | F14: 602 | G14: KAP SOFR 지수 | H14: 안전 | I14: 금리연계형/초단기채권
A15: 방어 | B15: A1 | C15: 현금성 | D15: A278620 | E15: PLUS 단기채권액티브 | F15: 532 | G15: KAP 투자적격 크레딧 채권 1년지수(A-이상,총수익) | H15: 안전 | I15: 국내채권_회사채
A16: 방어 | B16: A2 | C16: 국내 금리(국채·IG) | D16: A273130 | E16: KODEX 종합채권(AA-이상)액티브 | F16: 38484 | G16: KAP 한국종합채권지수 | H16: 안전 | I16: 국내채권_회사채 | J16: ★
A17: 방어 | B17: A2 | C17: 국내 금리(국채·IG) | D17: A385540 | E17: RISE 종합채권(A-이상)액티브 | F17: 17737 | G17: KIS 종합채권 지수(A-이상)(총수익지수) | H17: 안전 | I17: 국내채권_회사채
A18: 방어 | B18: A2 | C18: 국내 금리(국채·IG) | D18: A451540 | E18: TIGER 종합채권(AA-이상)액티브 | F18: 10134 | G18: KIS 종합채권 AA-이상 총수익 지수(Total return Index) | H18: 안전 | I18: 국내채권_회사채
A19: 방어 | B19: A2 | C19: 국내 금리(국채·IG) | D19: A438330 | E19: TIGER 투자등급회사채액티브 | F19: 6984 | G19: KIS 투자등급회사채 지수(총수익) | H19: 안전 | I19: 국내채권_회사채
A20: 방어 | B20: A2 | C20: 국내 금리(국채·IG) | D20: A114260 | E20: KODEX 국고채3년 | F20: 5353 | G20: MKF 국고채지수(총수익) | H20: 안전 | I20: 국내채권_종합
A21: 방어 | B21: A2 | C21: 국내 금리(국채·IG) | D21: A148070 | E21: KIWOOM 국고채10년 | F21: 4925 | G21: KIS 국고채 10년(총수익) | H21: 안전 | I21: 국내채권_종합
A22: 방어 | B22: A2 | C22: 국내 금리(국채·IG) | D22: A0016X0 | E22: SOL 중단기회사채(A-이상)액티브 | F22: 3669 | G22: KIS 중단기크레딧플러스채권(AA+~A-)지수(총수익) | H22: 안전 | I22: 국내채권_회사채
A23: 방어 | B23: A2 | C23: 국내 금리(국채·IG) | D23: A439870 | E23: KODEX 국고채30년액티브 | F23: 3549 | G23: KAP 국고채 30년 총수익 지수 | H23: 안전 | I23: 국내채권_종합
A24: 방어 | B24: A2 | C24: 국내 금리(국채·IG) | D24: A363570 | E24: KODEX 장기종합채권(AA-이상)액티브 | F24: 3200 | G24: KAP 한국장기종합채권지수(AA-이상, 총수익) | H24: 안전 | I24: 국내채권_회사채
A25: 방어 | B25: A2 | C25: 국내 금리(국채·IG) | D25: A302190 | E25: TIGER 중장기국채 | F25: 2950 | G25: KIS 국채 3-10년 지수(시장가격지수) | H25: 안전 | I25: 국내채권_종합
A26: 방어 | B26: A2 | C26: 국내 금리(국채·IG) | D26: A114100 | E26: RISE 국고채3년 | F26: 1798 | G26: KTB index(시장가격) | H26: 안전 | I26: 국내채권_종합
A27: 방어 | B27: A2 | C27: 국내 금리(국채·IG) | D27: A451530 | E27: TIGER 국고채30년스트립액티브 | F27: 1444 | G27: KIS STRIP 30Y Index(총수익지수) | H27: 안전 | I27: 국내채권_종합
A28: 방어 | B28: A2 | C28: 국내 금리(국채·IG) | D28: A298340 | E28: PLUS 국채선물3년 | F28: 600 | G28: F-KTB 지수 | H28: 안전 | I28: 국내채권_종합
... A32: 방어 | B32: A2 | C32: 국내 금리(국채·IG) | D32: A397420 | E32: RISE 국채선물5년추종 | F32: 52 | G32: 5년 국채선물 추종 지수 | H32: 안전 | I32: 국내채권_종합
A33: 방어 | B33: A3 | C33: 미국 금리(국채·IG) | D33: A453850 | E33: ACE 미국30년국채액티브(H) | F33: 18200 | G33: Bloomberg U.S Treasury 20+ Year Total Return Index | H33: 안전 | I33: 해외채권_종합 | J33: ★
A34: 방어 | B34: A3 | C34: 미국 금리(국채·IG) | D34: A458250 | E34: TIGER 미국30년국채스트립액티브(합성 H) | F34: 6231 | G34: ICE BofA Long US Treasury Principal STRIPS Index | H34: 안전 | I34: 해외채권_종합
A35: 방어 | B35: A3 | C35: 미국 금리(국채·IG) | D35: A484790 | E35: KODEX 미국30년국채액티브(H) | F35: 5934 | G35: KEDI-KAP 미국 국채 20+ 지수(TR) | H35: 안전 | I35: 해외채권_종합
A36: 방어 | B36: A3 | C36: 미국 금리(국채·IG) | D36: A472870 | E36: RISE 미국30년국채엔화노출(합성 H) | F36: 3570 | G36: KIS 미국채30년 엔화노출 지수(USD/JPY 헤지)(총수익지수) | H36: 안전 | I36: 해외채권_종합
A37: 방어 | B37: A3 | C37: 미국 금리(국채·IG) | D37: A476760 | E37: ACE 미국30년국채액티브 | F37: 3171 | G37: Bloomberg U.S Treasury 20+ Year Total Return Index | H37: 안전 | I37: 해외채권_종합
A38: 방어 | B38: A3 | C38: 미국 금리(국채·IG) | D38: A458260 | E38: TIGER 미국투자등급회사채액티브(H) | F38: 2883 | G38: iBoxx USD Liquid Investment Grade Index(Price Return) | H38: 안전 | I38: 해외채권_회사채
A39: 방어 | B39: A3 | C39: 미국 금리(국채·IG) | D39: A305080 | E39: TIGER 미국채10년선물 | F39: 2446 | G39: S&P 10-Year U.S. Treasury Note Futures(ER) | H39: 안전 | I39: 해외채권_종합
A40: 방어 | B40: A3 | C40: 미국 금리(국채·IG) | D40: A308620 | E40: KODEX 미국10년국채선물 | F40: 1138 | G40: S&P 10-Year U.S. Treasury Note Futures KRW(ER) | H40: 안전 | I40: 해외채권_종합
A41: 방어 | B41: A3 | C41: 미국 금리(국채·IG) | D41: A476750 | E41: ACE 미국30년국채엔화노출액티브(H) | F41: 860 | G41: Bloomberg U.S. Treasury 20+ Year Total Return Index T1530 JPY Currency Hedged | H41: 안전 | I41: 해외채권_종합
A42: 방어 | B42: A3 | C42: 미국 금리(국채·IG) | D42: A468630 | E42: KODEX iShares미국투자등급회사채액티브 | F42: 367 | G42: Markit iBoxx USD Liquid Investment Grade Index(Total Return) | H42: 안전 | I42: 해외채권_회사채
A43: 방어 | B43: A3 | C43: 미국 금리(국채·IG) | D43: A332620 | E43: PLUS 미국장기우량회사채 | F43: 208 | G43: ICE BofaAML 15+ Year AAA-A US Corporate Index(총수익지수) | H43: 안전 | I43: 해외채권_회사채
A44: 방어 | B44: A3 | C44: 미국 금리(국채·IG) | D44: A332610 | E44: PLUS 미국단기회사채(AAA~A) | F44: 131 | G44: ICE BofaAML 1-3 Year AAA-A US Corporate Index(총수익지수) | H44: 안전 | I44: 해외채권_회사채
A45: 방어 | B45: A3 | C45: 미국 금리(국채·IG) | D45: A267440 | E45: RISE 미국장기국채선물(H) | F45: 51 | G45: S&P U.S. Treasury Bond Futures Excess Return Index | H45: 안전 | I45: 해외채권_종합
A46: 방어 | B46: A4 | C46: 안전통화 | D46: A261240 | E46: KODEX 미국달러선물 | F46: 724 | G46: 미국달러 선물지수 | H46: 위험 | I46: FX 및 원자재 | J46: ★
A47: 방어 | B47: A4 | C47: 안전통화 | D47: A292560 | E47: TIGER 일본엔선물 | F47: 542 | G47: 엔선물지수 | H47: 위험 | I47: FX 및 원자재
A48: 방어 | B48: A4 | C48: 안전통화 | D48: A489000 | E48: PLUS 일본엔화초단기국채(합성) | F48: 219 | G48: KAP 일본 단기 국채 지수(총수익) | H48: 안전 | I48: 해외채권_종합
A49: 방어 | B49: A5 | C49: 금·인플레헤지 | D49: A411060 | E49: ACE KRX금현물 | F49: 52303 | G49: KRX 금현물지수 | H49: 위험 | I49: FX 및 원자재 | J49: ★
A50: 방어 | B50: A5 | C50: 금·인플레헤지 | D50: A144600 | E50: KODEX 은선물(H) | F50: 14590 | G50: S&P GSCI Silver Index(TR) | H50: 위험 | I50: FX 및 원자재
A51: 방어 | B51: A5 | C51: 금·인플레헤지 | D51: A132030 | E51: KODEX 골드선물(H) | F51: 4821 | G51: S&P GSCI Gold Index(TR) | H51: 위험 | I51: FX 및 원자재
A52: 방어 | B52: A5 | C52: 금·인플레헤지 | D52: A468370 | E52: KODEX iShares미국인플레이션국채액티브 | F52: 187 | G52: ICE U.S. Treasury Inflation Linked Bond Index(Total Return) | H52: 안전 | I52: 금리연계형/초단기채권
A53: 방어 | B53: A5 | C53: 금·인플레헤지 | D53: A430500 | E53: KIWOOM 물가채KIS | F53: 113 | G53: KIS TIPS 지수 (Total Return) | H53: 안전 | I53: 금리연계형/초단기채권
A54: 성장 | B54: B1 | C54: 한국주식(브로드·시클리컬·테마) | D54: A069500 | E54: KODEX 200 | F54: 164803 | G54: 코스피 200 | H54: 위험 | I54: 국내주식_지수 | J54: ★
A55: 성장 | B55: B1 | C55: 한국주식(브로드·시클리컬·테마) | D55: A229200 | E55: KODEX 코스닥150 | F55: 71839 | G55: 코스닥 150 | H55: 위험 | I55: 국내주식_지수
A56: 성장 | B56: B1 | C56: 한국주식(브로드·시클리컬·테마) | D56: A102110 | E56: TIGER 200 | F56: 67897 | G56: 코스피 200 | H56: 위험 | I56: 국내주식_지수
A57: 성장 | B57: B1 | C57: 한국주식(브로드·시클리컬·테마) | D57: A278530 | E57: KODEX 200TR | F57: 52559 | G57: 코스피 200 TR지수 | H57: 위험 | I57: 국내주식_지수
A58: 성장 | B58: B1 | C58: 한국주식(브로드·시클리컬·테마) | D58: A310970 | E58: TIGER MSCI Korea TR | F58: 39380 | G58: MSCI Korea TR Index | H58: 위험 | I58: 국내주식_지수
A59: 성장 | B59: B1 | C59: 한국주식(브로드·시클리컬·테마) | D59: A148020 | E59: RISE 200 | F59: 29007 | G59: 코스피 200 | H59: 위험 | I59: 국내주식_지수
A60: 성장 | B60: B1 | C60: 한국주식(브로드·시클리컬·테마) | D60: A102780 | E60: KODEX 삼성그룹 | F60: 23508 | G60: MKF 삼성그룹지수 | H60: 위험 | I60: 국내주식_섹터
A61: 성장 | B61: B1 | C61: 한국주식(브로드·시클리컬·테마) | D61: A232080 | E61: TIGER 코스닥150 | F61: 22098 | G61: 코스닥 150 | H61: 위험 | I61: 국내주식_지수
A62: 성장 | B62: B1 | C62: 한국주식(브로드·시클리컬·테마) | D62: A278540 | E62: KODEX MSCI Korea TR | F62: 21216 | G62: MSCI Korea TR Index | H62: 위험 | I62: 국내주식_지수
A63: 성장 | B63: B1 | C63: 한국주식(브로드·시클리컬·테마) | D63: A466920 | E63: SOL 조선TOP3플러스 | F63: 18733 | G63: FnGuide 조선TOP3플러스지수(PR) | H63: 위험 | I63: 국내주식_섹터
A64: 성장 | B64: B1 | C64: 한국주식(브로드·시클리컬·테마) | D64: A449450 | E64: PLUS K방산 | F64: 17803 | G64: FnGuide K-방위산업 지수 | H64: 위험 | I64: 국내주식_섹터
A65: 성장 | B65: B1 | C65: 한국주식(브로드·시클리컬·테마) | D65: A294400 | E65: KIWOOM 200TR | F65: 15375 | G65: 코스피 200 TR지수 | H65: 위험 | I65: 국내주식_지수
A66: 성장 | B66: B1 | C66: 한국주식(브로드·시클리컬·테마) | D66: A315930 | E66: KODEX Top5PlusTR | F66: 13675 | G66: FnGuide TOP 5 Plus Total Return 지수 | H66: 위험 | I66: 국내주식_섹터
... A87: 성장 | B87: B1 | C87: 한국주식(브로드·시클리컬·테마) | D87: A139240 | E87: TIGER 200 철강소재 | F87: 72 | G87: 코스피 200 철강/소재 | H87: 위험 | I87: 국내주식_섹터
A88: 성장 | B88: B2 | C88: 미국·선진 코어주식 | D88: A360750 | E88: TIGER 미국S&P500 | F88: 147821 | G88: S&P 500 | H88: 위험 | I88: 해외주식_지수 | J88: ★
A89: 성장 | B89: B2 | C89: 미국·선진 코어주식 | D89: A379800 | E89: KODEX 미국S&P500 | F89: 81089 | G89: S&P 500 | H89: 위험 | I89: 해외주식_지수
A90: 성장 | B90: B2 | C90: 미국·선진 코어주식 | D90: A133690 | E90: TIGER 미국나스닥100 | F90: 79730 | G90: NASDAQ 100 | H90: 위험 | I90: 해외주식_지수
A91: 성장 | B91: B2 | C91: 미국·선진 코어주식 | D91: A379810 | E91: KODEX 미국나스닥100 | F91: 55319 | G91: NASDAQ 100 | H91: 위험 | I91: 해외주식_지수
A92: 성장 | B92: B2 | C92: 미국·선진 코어주식 | D92: A360200 | E92: ACE 미국S&P500 | F92: 33475 | G92: S&P 500 | H92: 위험 | I92: 해외주식_지수
A93: 성장 | B93: B2 | C93: 미국·선진 코어주식 | D93: A367380 | E93: ACE 미국나스닥100 | F93: 27323 | G93: NASDAQ 100 | H93: 위험 | I93: 해외주식_지수
A94: 성장 | B94: B2 | C94: 미국·선진 코어주식 | D94: A379780 | E94: RISE 미국S&P500 | F94: 14147 | G94: S&P 500 | H94: 위험 | I94: 해외주식_지수
A95: 성장 | B95: B2 | C95: 미국·선진 코어주식 | D95: A449180 | E95: KODEX 미국S&P500(H) | F95: 6946 | G95: S&P 500 | H95: 위험 | I95: 해외주식_지수
A96: 성장 | B96: B2 | C96: 미국·선진 코어주식 | D96: A251350 | E96: KODEX 선진국MSCI World | F96: 4913 | G96: MSCI World | H96: 위험 | I96: 해외주식_지수
A97: 성장 | B97: B2 | C97: 미국·선진 코어주식 | D97: A448290 | E97: TIGER 미국S&P500TR(H) | F97: 4371 | G97: S&P 500 Total Return Index | H97: 위험 | I97: 해외주식_지수
A98: 성장 | B98: B2 | C98: 미국·선진 코어주식 | D98: A448300 | E98: TIGER 미국나스닥100TR(H) | F98: 2963 | G98: NASDAQ-100 Total Return Index | H98: 위험 | I98: 해외주식_지수
A99: 성장 | B99: B2 | C99: 미국·선진 코어주식 | D99: A219480 | E99: KODEX 미국S&P500선물(H) | F99: 1437 | G99: S&P 500 Futures Total Return Index | H99: 위험 | I99: 해외주식_지수
A100: 성장 | B100: B2 | C100: 미국·선진 코어주식 | D100: A245340 | E100: TIGER 미국다우존스30 | F100: 1412 | G100: Dow Jones Industrial Average | H100: 위험 | I100: 해외주식_지수
... A111: 성장 | B111: B2 | C111: 미국·선진 코어주식 | D111: A189400 | E111: PLUS 글로벌MSCI(합성 H) | F111: 70 | G111: MSCI ACWI Index | H111: 위험 | I111: 해외주식_지수
A112: 성장 | B112: B3 | C112: 글로벌 테크·반도체·성장테마 | D112: A381170 | E112: TIGER 미국테크TOP10 INDXX | F112: 38009 | G112: Indxx US Tech Top 10 Index | H112: 위험 | I112: 해외주식_섹터 | J112: ★
A113: 성장 | B113: B3 | C113: 글로벌 테크·반도체·성장테마 | D113: A091160 | E113: KODEX 반도체 | F113: 36019 | G113: KRX 반도체 | H113: 위험 | I113: 국내주식_섹터
A114: 성장 | B114: B3 | C114: 글로벌 테크·반도체·성장테마 | D114: A381180 | E114: TIGER 미국필라델피아반도체나스닥 | F114: 34100 | G114: PHLX Semiconductor Sector Index | H114: 위험 | I114: 해외주식_지수
A115: 성장 | B115: B3 | C115: 글로벌 테크·반도체·성장테마 | D115: A395160 | E115: KODEX AI반도체 | F115: 20947 | G115: FnGuide AI반도체지수 | H115: 위험 | I115: 국내주식_섹터
A116: 성장 | B116: B3 | C116: 글로벌 테크·반도체·성장테마 | D116: A305720 | E116: KODEX 2차전지산업 | F116: 18187 | G116: FnGuide 2차전지 산업 지수 | H116: 위험 | I116: 국내주식_섹터
A117: 성장 | B117: B3 | C117: 글로벌 테크·반도체·성장테마 | D117: A487240 | E117: KODEX AI전력핵심설비 | F117: 15914 | G117: iSelect AI 전력핵심설비 지수(Price Return) | H117: 위험 | I117: 국내주식_섹터
A118: 성장 | B118: B3 | C118: 글로벌 테크·반도체·성장테마 | D118: A395270 | E118: HANARO Fn K-반도체 | F118: 14664 | G118: FnGuide K-반도체 지수 (시장가격) | H118: 위험 | I118: 국내주식_섹터
A119: 성장 | B119: B3 | C119: 글로벌 테크·반도체·성장테마 | D119: A487230 | E119: KODEX 미국AI전력핵심인프라 | F119: 13631 | G119: iSelect 미국AI전력핵심인프라 지수(Price Return) | H119: 위험 | I119: 해외주식_섹터
A120: 성장 | B120: B3 | C120: 글로벌 테크·반도체·성장테마 | D120: A371460 | E120: TIGER 차이나전기차SOLACTIVE | F120: 13027 | G120: Solactive China Electric Vehicle and Battery Index(PR) | H120: 위험 | I120: 해외주식_섹터
A121: 성장 | B121: B3 | C121: 글로벌 테크·반도체·성장테마 | D121: A457480 | E121: ACE 테슬라밸류체인액티브 | F121: 11487 | G121: Bloomberg EV Supporters Plus Tesla Price Return Index | H121: 위험 | I121: 해외주식_섹터
A122: 성장 | B122: B3 | C122: 글로벌 테크·반도체·성장테마 | D122: A305540 | E122: TIGER 2차전지테마 | F122: 11376 | G122: WISE 2차전지 테마 지수 | H122: 위험 | I122: 국내주식_섹터
A123: 성장 | B123: B3 | C123: 글로벌 테크·반도체·성장테마 | D123: A456600 | E123: TIME 글로벌AI인공지능액티브 | F123: 10744 | G123: Solactive Global Artificial Intelligence 지수 | H123: 위험 | I123: 해외주식_섹터
A124: 성장 | B124: B3 | C124: 글로벌 테크·반도체·성장테마 | D124: A445290 | E124: KODEX 로봇액티브 | F124: 9793 | G124: iSelect K-로봇테마 지수 | H124: 위험 | I124: 국내주식_섹터
... A135: 성장 | B135: B3 | C135: 글로벌 테크·반도체·성장테마 | D135: A185680 | E135: KODEX 미국S&P바이오(합성) | F135: 200 | G135: S&P Biotechnology Select Industry Index | H135: 위험 | I135: 해외주식_섹터
A136: 성장 | B136: B4 | C136: 중국주식 | D136: A371160 | E136: TIGER 차이나항셍테크 | F136: 9134 | G136: Hang Seng TECH Index | H136: 위험 | I136: 해외주식_지수 | J136: ★
A137: 성장 | B137: B4 | C137: 중국주식 | D137: A283580 | E137: KODEX 차이나CSI300 | F137: 2825 | G137: CSI 300 | H137: 위험 | I137: 해외주식_지수
A138: 성장 | B138: B4 | C138: 중국주식 | D138: A414780 | E138: TIGER 차이나과창판STAR50(합성) | F138: 2068 | G138: STAR 50 Index(Price Return) | H138: 위험 | I138: 해외주식_지수
A139: 성장 | B139: B4 | C139: 중국주식 | D139: A372330 | E139: KODEX 차이나항셍테크 | F139: 1627 | G139: Hang Seng TECH Index | H139: 위험 | I139: 해외주식_지수
A140: 성장 | B140: B4 | C140: 중국주식 | D140: A192090 | E140: TIGER 차이나CSI300 | F140: 1575 | G140: CSI 300 | H140: 위험 | I140: 해외주식_지수
A141: 성장 | B141: B4 | C141: 중국주식 | D141: A168580 | E141: ACE 중국본토CSI300 | F141: 1301 | G141: CSI 300 | H141: 위험 | I141: 해외주식_지수
A142: 성장 | B142: B4 | C142: 중국주식 | D142: A099140 | E142: KODEX 차이나H | F142: 437 | G142: HSCEI (Hang Seng China Enterprise Index) | H142: 위험 | I142: 해외주식_지수
A143: 성장 | B143: B4 | C143: 중국주식 | D143: A245360 | E143: TIGER 차이나HSCEI | F143: 400 | G143: HSCEI (Hang Seng China Enterprise Index) | H143: 위험 | I143: 해외주식_지수
...

Sheet 버킷요약
A1: 버킷 | B1: 버킷명 | C1: 진영 | D1: 종목수 | E1: AUM합(억원) | F1: AUM비중 | G1: 대표ETF
A2: A1 | B2: 현금성 | C2: 방어 | D2: =COUNTIF(버킷분류!B2:B189,A2) -> 14 | E2: =SUMIF(버킷분류!B2:B189,A2,버킷분류!F2:F189) -> 273467 | F2: =E2/$E$17 -> 0.13386805 | G2: KODEX CD금리액티브(합성)
A3: A2 | B3: 국내 금리(국채·IG) | C3: 방어 | D3: =COUNTIF(버킷분류!B2:B189,A3) -> 17 | E3: =SUMIF(버킷분류!B2:B189,A3,버킷분류!F2:F189) -> 102228 | F3: =E3/$E$17 -> 0.050042833 | G3: KODEX 종합채권(AA-이상)액티브
A4: A3 | B4: 미국 금리(국채·IG) | C4: 방어 | D4: =COUNTIF(버킷분류!B2:B189,A4) -> 13 | E4: =SUMIF(버킷분류!B2:B189,A4,버킷분류!F2:F189) -> 45190 | F4: =E4/$E$17 -> 0.02212149 | G4: ACE 미국30년국채액티브(H)
A5: A4 | B5: 안전통화 | C5: 방어 | D5: =COUNTIF(버킷분류!B2:B189,A5) -> 3 | E5: =SUMIF(버킷분류!B2:B189,A5,버킷분류!F2:F189) -> 1485 | F5: =E5/$E$17 -> 0.00072693985 | G5: KODEX 미국달러선물
A6: A5 | B6: 금·인플레헤지 | C6: 방어 | D6: =COUNTIF(버킷분류!B2:B189,A6) -> 5 | E6: =SUMIF(버킷분류!B2:B189,A6,버킷분류!F2:F189) -> 72014 | F6: =E6/$E$17 -> 0.035252422 | G6: ACE KRX금현물
A7: B1 | B7: 한국주식(브로드·시클리컬·테마) | C7: 성장 | D7: =COUNTIF(버킷분류!B2:B189,A7) -> 34 | E7: =SUMIF(버킷분류!B2:B189,A7,버킷분류!F2:F189) -> 637558 | F7: =E7/$E$17 -> 0.31209853 | G7: KODEX 200
A8: B2 | B8: 미국·선진 코어주식 | C8: 성장 | D8: =COUNTIF(버킷분류!B2:B189,A8) -> 24 | E8: =SUMIF(버킷분류!B2:B189,A8,버킷분류!F2:F189) -> 466250 | F8: =E8/$E$17 -> 0.22823953 | G8: TIGER 미국S&P500
A9: B3 | B9: 글로벌 테크·반도체·성장테마 | C9: 성장 | D9: =COUNTIF(버킷분류!B2:B189,A9) -> 24 | E9: =SUMIF(버킷분류!B2:B189,A9,버킷분류!F2:F189) -> 311193 | F9: =E9/$E$17 -> 0.15233575 | G9: TIGER 미국테크TOP10 INDXX
A10: B4 | B10: 중국주식 | C10: 성장 | D10: =COUNTIF(버킷분류!B2:B189,A10) -> 10 | E10: =SUMIF(버킷분류!B2:B189,A10,버킷분류!F2:F189) -> 19658 | F10: =E10/$E$17 -> 0.0096230193 | G10: TIGER 차이나항셍테크
A11: B5 | B11: 기타 해외주식 | C11: 성장 | D11: =COUNTIF(버킷분류!B2:B189,A11) -> 18 | E11: =SUMIF(버킷분류!B2:B189,A11,버킷분류!F2:F189) -> 21328 | F11: =E11/$E$17 -> 0.010440521 | G11: TIGER 일본니케이225
A12: B6 | B12: 방어적 주식(배당·저변동) | C12: 성장 | D12: =COUNTIF(버킷분류!B2:B189,A12) -> 17 | E12: =SUMIF(버킷분류!B2:B189,A12,버킷분류!F2:F189) -> 86293 | F12: =E12/$E$17 -> 0.042242303 | G12: TIGER 미국배당다우존스
A13: B7 | B13: 리츠(부동산) | C13: 성장 | D13: =COUNTIF(버킷분류!B2:B189,A13) -> 2 | E13: =SUMIF(버킷분류!B2:B189,A13,버킷분류!F2:F189) -> 1998 | F13: =E13/$E$17 -> 0.00097806453 | G13: TIGER 미국MSCI리츠(합성 H)
A14: B8 | B14: 경기민감 원자재·에너지 | C14: 성장 | D14: =COUNTIF(버킷분류!B2:B189,A14) -> 4 | E14: =SUMIF(버킷분류!B2:B189,A14,버킷분류!F2:F189) -> 2378 | F14: =E14/$E$17 -> 0.0011640828 | G14: KODEX WTI원유선물(H)
A15: B9 | B15: 위험 크레딧(하이일드) | C15: 성장 | D15: =COUNTIF(버킷분류!B2:B189,A15) -> 3 | E15: =SUMIF(버킷분류!B2:B189,A15,버킷분류!F2:F189) -> 1770 | F15: =E15/$E$17 -> 0.00086645356 | G15: KODEX iShares미국하이일드액티브
A17: 합계 | D17: =SUM(D2:D15) -> 188 | E17: =SUM(E2:E15) -> 2042810
